{"resourceType":"ValueSet","id":"17405","date":"2020-12-04T00:00:00+01:00","copyright":"The International Union of Pure and Applied Chemistry (IUPAC) and the International Federation of Clinical Chemistry and laboratory medicine (IFCC)","compose":{"include":[{"system":"https://www.npu-terminology.org/","concept":[{"code":"NPU17405"},{"code":"NPU17374"},{"code":"NPU22097"},{"code":"NPU22098"},{"code":"NPU17382"},{"code":"NPU17375"},{"code":"NPU17379"},{"code":"NPU17381"},{"code":"NPU17383"},{"code":"NPU17384"},{"code":"NPU17376"},{"code":"NPU17378"},{"code":"NPU17380"},{"code":"NPU17385"},{"code":"NPU17394"},{"code":"NPU17402"},{"code":"NPU17395"},{"code":"NPU17399"},{"code":"NPU17401"},{"code":"NPU17403"},{"code":"NPU17404"},{"code":"NPU17396"},{"code":"NPU17398"},{"code":"NPU17400"},{"code":"NPU17373"}]}]}}