{"resourceType":"ValueSet","id":"5295","date":"2017-04-20T00:00:00+02:00","copyright":"The International Union of Pure and Applied Chemistry (IUPAC) and the International Federation of Clinical Chemistry and laboratory medicine (IFCC)","compose":{"include":[{"system":"https://www.npu-terminology.org/","concept":[{"code":"DNK05295"},{"code":"NPU17485"},{"code":"NPU16227"},{"code":"NPU12472"},{"code":"NPU16222"},{"code":"NPU12415"},{"code":"NPU16231"},{"code":"NPU12473"},{"code":"NPU17471"},{"code":"DNK05296"}]}]}}